cyclo/__init__.py
cyclo/cyclo.py
cyclo-0.0.2.dist-info/LICENSE
cyclo-0.0.2.dist-info/METADATA
cyclo-0.0.2.dist-info/WHEEL
cyclo-0.0.2.dist-info/top_level.txt
cyclo-0.0.2.dist-info/RECORD
