Metadata-Version: 2.1
Name: cyclo
Version: 0.0.2
Summary: solving cyclotomic equation by radicals
Home-page: https://github.com/tt-nakamura/cyclo
Author: Takahiro Nakamura
Author-email: a41757@gmail.com
License: UNKNOWN
Project-URL: Bug Tracker, https://github.com/tt-nakamura/cyclo/issues
Platform: UNKNOWN
Classifier: Programming Language :: Python :: 3
Classifier: License :: OSI Approved :: MIT License
Classifier: Operating System :: OS Independent
Requires-Python: >=3.6
License-File: LICENSE
